pyldfire.py
pyldfire-9.0.dist-info/LICENSE
pyldfire-9.0.dist-info/METADATA
pyldfire-9.0.dist-info/WHEEL
pyldfire-9.0.dist-info/top_level.txt
pyldfire-9.0.dist-info/RECORD
