Metadata-Version: 2.1
Name: pyldfire
Version: 9.0
Summary: A Python module for Palo Alto Networks' WildFire API
Home-page: https://github.com/seanthegeek/pyldfire
Author: Sean Whalen
Author-email: whalenster@gmail.com
License: Apache 2.0
Keywords: PaloAltoNetworks WildFire API Malware Sandbox
Platform: UNKNOWN
Classifier: Development Status :: 5 - Production/Stable
Classifier: Topic :: Security
Classifier: Intended Audience :: Developers
Classifier: Intended Audience :: System Administrators
Classifier: Operating System :: OS Independent
Classifier: License :: OSI Approved :: Apache Software License
Classifier: Programming Language :: Python :: 2
Classifier: Programming Language :: Python :: 2.6
Classifier: Programming Language :: Python :: 2.7
Classifier: Programming Language :: Python :: 3
Classifier: Programming Language :: Python :: 3.3
Classifier: Programming Language :: Python :: 3.4
Classifier: Programming Language :: Python :: 3.5
Requires-Dist: requests
Requires-Dist: xmltodict
